spherical_functions/Wigner_coefficients.npy
spherical_functions/__init__.py
spherical_functions/_generate_coefficients.py
spherical_functions/binomial_coefficients.npy
spherical_functions/ladder_operator_coefficients.npy
spherical_functions/mode_conversions.py
spherical_functions/multiplication.py
spherical_functions/SWSH/__init__.py
spherical_functions/SWSH_grids/__init__.py
spherical_functions/SWSH_grids/algebra.py
spherical_functions/SWSH_grids/ufuncs.py
spherical_functions/SWSH_grids/utilities.py
spherical_functions/SWSH_modes/__init__.py
spherical_functions/SWSH_modes/algebra.py
spherical_functions/SWSH_modes/derivatives.py
spherical_functions/SWSH_modes/ufuncs.py
spherical_functions/SWSH_modes/utilities.py
spherical_functions/WignerD/WignerDRecursion.py
spherical_functions/WignerD/__init__.py
spherical_functions/recursions/__init__.py
spherical_functions/recursions/associated_legendre_functions.py
spherical_functions/recursions/complex_powers.py
spherical_functions/recursions/wigner3j.py
spherical_functions/recursions/wignerH.py
spherical_functions-2023.0.2.dist-info/METADATA
spherical_functions-2023.0.2.dist-info/WHEEL
spherical_functions-2023.0.2.dist-info/licenses/LICENSE
spherical_functions-2023.0.2.dist-info/RECORD
