Metadata-Version: 2.4
Name: spherical-functions
Version: 2023.0.2
Summary: Python/numba implementation of Wigner D Matrices, spin-weighted spherical harmonics, and associated functions
Author-email: Michael Boyle <mob22@cornell.edu>
License: MIT
License-File: LICENSE
Requires-Python: >=3.10
Requires-Dist: numba>=0.55
Requires-Dist: numpy-quaternion>=2022
Requires-Dist: numpy>=1.20
Requires-Dist: scipy>=1.0
Requires-Dist: spinsfast>=2022
Provides-Extra: dev
Requires-Dist: black>=22.1; extra == 'dev'
Requires-Dist: line-profiler>=3.5.0; extra == 'dev'
Requires-Dist: pytest-cov>=2.10.1; extra == 'dev'
Requires-Dist: pytest>=7.0; extra == 'dev'
Requires-Dist: sympy>=1.10; extra == 'dev'
